shreycriclivemac.py
shreycriclivemac-0.4.dist-info/METADATA
shreycriclivemac-0.4.dist-info/WHEEL
shreycriclivemac-0.4.dist-info/entry_points.txt
shreycriclivemac-0.4.dist-info/top_level.txt
shreycriclivemac-0.4.dist-info/RECORD
