Metadata-Version: 2.1
Name: shreycriclivemac
Version: 0.4
Requires-Dist: requests
Requires-Dist: lxml
Requires-Dist: beautifulsoup4
